api/__init__.py
api/v2/__init__.py
api/v2/auth_gateway_service_pb2.py
api/v2/auth_gateway_service_pb2_grpc.py
api/v2/dashboard_service_pb2.py
api/v2/user_gateway_service_pb2.py
api/v2/user_gateway_service_pb2_grpc.py
api/v2/workflow_gateway_service_pb2.py
api/v2/workflow_gateway_service_pb2_grpc.py
auth/__init__.py
auth/v2/__init__.py
auth/v2/auth_service_pb2.py
auth/v2/auth_service_pb2_grpc.py
auth/v2/token_pb2.py
common/__init__.py
common/v2/__init__.py
common/v2/common_pb2.py
google/__init__.py
google/api/__init__.py
google/api/annotations_pb2.py
google/api/client_pb2.py
google/api/field_behavior_pb2.py
google/api/field_info_pb2.py
google/api/http_pb2.py
google/api/httpbody_pb2.py
google/api/launch_stage_pb2.py
google/api/resource_pb2.py
google/api/visibility_pb2.py
google/api/expr/__init__.py
google/api/expr/v1alpha1/__init__.py
google/api/expr/v1alpha1/checked_pb2.py
google/api/expr/v1alpha1/eval_pb2.py
google/api/expr/v1alpha1/explain_pb2.py
google/api/expr/v1alpha1/syntax_pb2.py
google/api/expr/v1alpha1/value_pb2.py
google/api/expr/v1beta1/__init__.py
google/api/expr/v1beta1/decl_pb2.py
google/api/expr/v1beta1/eval_pb2.py
google/api/expr/v1beta1/expr_pb2.py
google/api/expr/v1beta1/source_pb2.py
google/api/expr/v1beta1/value_pb2.py
google/bytestream/__init__.py
google/bytestream/bytestream_pb2.py
google/geo/__init__.py
google/geo/type/__init__.py
google/geo/type/viewport_pb2.py
google/longrunning/__init__.py
google/longrunning/operations_pb2.py
google/rpc/__init__.py
google/rpc/code_pb2.py
google/rpc/error_details_pb2.py
google/rpc/status_pb2.py
google/rpc/context/__init__.py
google/rpc/context/attribute_context_pb2.py
google/type/__init__.py
google/type/calendar_period_pb2.py
google/type/color_pb2.py
google/type/date_pb2.py
google/type/datetime_pb2.py
google/type/dayofweek_pb2.py
google/type/decimal_pb2.py
google/type/expr_pb2.py
google/type/fraction_pb2.py
google/type/interval_pb2.py
google/type/latlng_pb2.py
google/type/localized_text_pb2.py
spounge_proto_py-0.2.9.dist-info/licenses/LICENSE
spounge_proto_py-0.2.9.dist-info/METADATA
spounge_proto_py-0.2.9.dist-info/WHEEL
spounge_proto_py-0.2.9.dist-info/top_level.txt
spounge_proto_py-0.2.9.dist-info/RECORD
